{
    "activation": "gelu",
    "batch_size": 32,
    "change_output": true,
    "comment": "finetuning through classification",
    "config_filepath": "config_files/spes_finetune_config.json",
    "console": false,
    "d_model": 64,
    "data_class": "spes",
    "data_dir": "classification_datasets/SPES",
    "data_window_len": null,
    "dim_feedforward": 256,
    "dropout": 0.1,
    "early_stopping_delta": 0,
    "early_stopping_patience": 10,
    "end_hint": 0.0,
    "epochs": 100,
    "exclude_feats": null,
    "experiment_name": "",
    "freeze": false,
    "global_reg": false,
    "gpu": "0",
    "harden": false,
    "initial_timestamp": "2024-11-10_15-39-48",
    "key_metric": "accuracy",
    "l2_reg": 0,
    "labels": null,
    "limit_size": null,
    "load_model": "output/spes/pretrained/_2024-11-09_15-26-47_XB4/checkpoints/model_best.pth",
    "lr": 0.001,
    "lr_factor": [
        0.1
    ],
    "lr_step": [
        1000000
    ],
    "mask_distribution": "geometric",
    "mask_feats": [
        0,
        1
    ],
    "mask_mode": "separate",
    "masking_ratio": 0.15,
    "max_seq_len": 487,
    "mean_mask_length": 3,
    "model": "transformer",
    "n_proc": -1,
    "no_timestamp": false,
    "norm_from": null,
    "normalization": "standardization",
    "normalization_layer": "BatchNorm",
    "num_classes": 2,
    "num_heads": 8,
    "num_layers": 3,
    "num_workers": 4,
    "optimizer": "Adam",
    "output_dir": "output/spes/pretrained/_2024-11-10_15-39-48_p2Q",
    "pattern": "TRAIN",
    "pos_encoding": "learnable",
    "pos_weight": 20.0,
    "pred_dir": "output/spes/pretrained/_2024-11-10_15-39-48_p2Q/predictions",
    "print_interval": 5,
    "records_file": "classification_records.xls",
    "resume": false,
    "save_all": false,
    "save_dir": "output/spes/pretrained/_2024-11-10_15-39-48_p2Q/checkpoints",
    "seed": null,
    "start_hint": 0.0,
    "subsample_factor": null,
    "task": "classification",
    "tensorboard_dir": "output/spes/pretrained/_2024-11-10_15-39-48_p2Q/tb_summaries",
    "test_from": null,
    "test_only": null,
    "test_pattern": null,
    "test_ratio": 0,
    "val_interval": 2,
    "val_pattern": "TEST",
    "val_ratio": 0
}